simplipy/__init__.py
simplipy/__main__.py
simplipy/asset_manager.py
simplipy/engine.py
simplipy/io.py
simplipy/operators.py
simplipy/utils.py
simplipy-0.2.11.dist-info/licenses/LICENSE
simplipy-0.2.11.dist-info/METADATA
simplipy-0.2.11.dist-info/WHEEL
simplipy-0.2.11.dist-info/entry_points.txt
simplipy-0.2.11.dist-info/top_level.txt
simplipy-0.2.11.dist-info/RECORD
