Metadata-Version: 2.4
Name: simplipy
Version: 0.2.11
Summary: Efficient Simplification of Mathematical Expressions
Author: Paul Saegert
License-Expression: MIT
Project-URL: Homepage, https://github.com/psaegert/simplipy
Project-URL: Issues, https://github.com/psaegert/simplipy/issues
Project-URL: PyPI, https://pypi.org/project/simplipy/
Project-URL: ReadtheDocs, https://simplipy.readthedocs.io/
Requires-Python: >=3.11
License-File: LICENSE
Requires-Dist: huggingface_hub
Requires-Dist: numpy
Requires-Dist: pyyaml
Requires-Dist: scipy
Requires-Dist: tqdm
Provides-Extra: dev
Requires-Dist: pre-commit; extra == "dev"
Requires-Dist: pytest; extra == "dev"
Requires-Dist: pytest-cov; extra == "dev"
Requires-Dist: mypy; extra == "dev"
Requires-Dist: flake8; extra == "dev"
Requires-Dist: pygount; extra == "dev"
Requires-Dist: types-setuptools; extra == "dev"
Requires-Dist: types-tqdm; extra == "dev"
Requires-Dist: types-toml; extra == "dev"
Requires-Dist: types-PyYAML; extra == "dev"
Requires-Dist: radon; extra == "dev"
Provides-Extra: torch
Requires-Dist: torch>=1.0.0; extra == "torch"
Dynamic: license-file
